odoo/addons/shopinvader_quotation_portal_mode/README.rst
odoo/addons/shopinvader_quotation_portal_mode/__init__.py
odoo/addons/shopinvader_quotation_portal_mode/__manifest__.py
odoo/addons/shopinvader_quotation_portal_mode/i18n/shopinvader_quotation_portal_mode.pot
odoo/addons/shopinvader_quotation_portal_mode/readme/CONTRIBUTORS.rst
odoo/addons/shopinvader_quotation_portal_mode/readme/DESCRIPTION.rst
odoo/addons/shopinvader_quotation_portal_mode/services/__init__.py
odoo/addons/shopinvader_quotation_portal_mode/services/quotation.py
odoo/addons/shopinvader_quotation_portal_mode/static/description/index.html
odoo/addons/shopinvader_quotation_portal_mode/tests/__init__.py
odoo/addons/shopinvader_quotation_portal_mode/tests/test_quotations.py
odoo14_addon_shopinvader_quotation_portal_mode-14.0.1.0.1.dist-info/METADATA
odoo14_addon_shopinvader_quotation_portal_mode-14.0.1.0.1.dist-info/WHEEL
odoo14_addon_shopinvader_quotation_portal_mode-14.0.1.0.1.dist-info/top_level.txt
odoo14_addon_shopinvader_quotation_portal_mode-14.0.1.0.1.dist-info/RECORD
