Metadata-Version: 2.1
Name: odoo14-addon-shopinvader-quotation-portal-mode
Version: 14.0.1.0.1
Summary: Enable portal-like features to quotations
Home-page: https://github.com/shopinvader/odoo-shopinvader
Author: Camptocamp
License: AGPL-3
Platform: UNKNOWN
Classifier: Programming Language :: Python
Classifier: Framework :: Odoo
Classifier: Framework :: Odoo :: 14.0
Classifier: License :: OSI Approved :: GNU Affero General Public License v3
Requires-Python: >=3.6
Requires-Dist: odoo14-addon-shopinvader-portal-mode
Requires-Dist: odoo14-addon-shopinvader-quotation
Requires-Dist: odoo (<14.1dev,>=14.0a)
